{
  "fin-default": {
    "Primary": {
      "Hellblau": {
        "value": "#89a7c9",
        "type": "color"
      },
      "Dunkelblau": {
        "value": "#263f6f",
        "type": "color"
      },
      "Pink": {
        "value": "#cc4182",
        "type": "color"
      },
      "Pink - Limonade": {
        "value": "#f1cbdc",
        "type": "color"
      },
      "Pink - Rouge": {
        "value": "#993a66",
        "type": "color"
      },
      "Pink - Wein": {
        "value": "#6c2b53",
        "type": "color"
      },
      "Weiss": {
        "value": "#ffffff",
        "type": "color"
      },
      "Schwarz": {
        "value": "#0d1626",
        "type": "color"
      }
    },
    "Neutral": {
      "Neutral 1": {
        "value": "#f5f6f7",
        "type": "color"
      },
      "Neutral 2": {
        "value": "#eceef0",
        "type": "color"
      },
      "Neutral 3": {
        "value": "#d3d7db",
        "type": "color"
      },
      "Neutral 4": {
        "value": "#b3b9c1",
        "type": "color"
      },
      "Neutral 5": {
        "value": "#6e7785",
        "type": "color"
      }
    },
    "Semantic": {
      "Lagune": {
        "value": "#60afc9",
        "type": "color"
      },
      "Lagune - Eis": {
        "value": "#c5e1eb",
        "type": "color"
      },
      "Petrol": {
        "value": "#78bf93",
        "type": "color"
      },
      "Petrol - Seegrün": {
        "value": "#cde7d7",
        "type": "color"
      },
      "Petrol - Kobold": {
        "value": "#346f4b",
        "type": "color"
      },
      "Gold": {
        "value": "#baae46",
        "type": "color"
      },
      "Gold - Khaki": {
        "value": "#ebe8be",
        "type": "color"
      },
      "Gold - Oliv": {
        "value": "#6e6935",
        "type": "color"
      },
      "Rot": {
        "value": "#e25646",
        "type": "color"
      },
      "Rot - Lachs": {
        "value": "#fabfb9",
        "type": "color"
      },
      "Rot - Sangria": {
        "value": "#91372d",
        "type": "color"
      },
      "Lagune - Ozean": {
        "value": "#396777",
        "type": "color"
      }
    },
    "Others": {
      "Pfirsich": {
        "value": "#ffd3a8",
        "type": "color"
      },
      "Aprikose": {
        "value": "#f29944",
        "type": "color"
      },
      "Haselnuss": {
        "value": "#804309",
        "type": "color"
      },
      "AG Grid Hover": {
        "value": "#fafafa",
        "type": "color"
      },
      "AG Grid Selected": {
        "value": "#eeeeee",
        "type": "color"
      },
      "_Component Board Border": {
        "value": "#263f6f40",
        "type": "color"
      }
    },
    "Table Dropdown Shadow": {
      "value": {
        "color": "#00000033",
        "type": "dropShadow",
        "x": 0,
        "y": 2,
        "blur": 6,
        "spread": 0
      },
      "type": "boxShadow"
    },
    "Button Dropdown Shadow": {
      "value": {
        "color": "#00000040",
        "type": "dropShadow",
        "x": 1,
        "y": 2,
        "blur": 8,
        "spread": 0
      },
      "type": "boxShadow"
    },
    "_Component Frame Shadow": {
      "value": {
        "color": "#abccf230",
        "type": "dropShadow",
        "x": 3,
        "y": 3,
        "blur": 25,
        "spread": 2
      },
      "type": "boxShadow"
    },
    "Material Dropdown Shadow": {
      "value": {
        "color": "#00000040",
        "type": "dropShadow",
        "x": 0,
        "y": 2,
        "blur": 4,
        "spread": 1
      },
      "type": "boxShadow"
    },
    "Popup Shadow": {
      "value": {
        "color": "#00000033",
        "type": "dropShadow",
        "x": 2,
        "y": 2,
        "blur": 25,
        "spread": 0
      },
      "type": "boxShadow"
    },
    "fontFamilies": {
      "roboto-condensed": {
        "value": "Roboto Condensed",
        "type": "fontFamilies"
      },
      "roboto": {
        "value": "Roboto",
        "type": "fontFamilies"
      }
    },
    "lineHeights": {
      "0": {
        "value": "40",
        "type": "lineHeights"
      },
      "1": {
        "value": "20",
        "type": "lineHeights"
      },
      "2": {
        "value": "AUTO",
        "type": "lineHeights"
      },
      "3": {
        "value": "16",
        "type": "lineHeights"
      }
    },
    "fontWeights": {
      "roboto-condensed-0": {
        "value": "Light",
        "type": "fontWeights"
      },
      "roboto-condensed-1": {
        "value": "Regular",
        "type": "fontWeights"
      },
      "roboto-2": {
        "value": "Medium",
        "type": "fontWeights"
      },
      "roboto-3": {
        "value": "Bold",
        "type": "fontWeights"
      },
      "roboto-4": {
        "value": "Regular",
        "type": "fontWeights"
      },
      "roboto-5": {
        "value": "Italic",
        "type": "fontWeights"
      }
    },
    "fontSize": {
      "0": {
        "value": "12",
        "type": "fontSizes"
      },
      "1": {
        "value": "14",
        "type": "fontSizes"
      },
      "2": {
        "value": "34",
        "type": "fontSizes"
      },
      "3": {
        "value": "36",
        "type": "fontSizes"
      }
    },
    "letterSpacing": {
      "0": {
        "value": "0%",
        "type": "letterSpacing"
      }
    },
    "paragraphSpacing": {
      "0": {
        "value": "0",
        "type": "paragraphSpacing"
      }
    },
    "Titles": {
      "Seitentitel": {
        "value": {
          "fontFamily": "$fontFamilies.roboto-condensed",
          "fontWeight": "$fontWeights.roboto-condensed-0",
          "lineHeight": "$lineHeights.0",
          "fontSize": "$fontSize.2",
          "letterSpacing": "$letterSpacing.0",
          "paragraphSpacing": "$paragraphSpacing.0",
          "textCase": "$textCase.uppercase",
          "textDecoration": "$textDecoration.none"
        },
        "type": "typography"
      },
      "Sektionstitel": {
        "value": {
          "fontFamily": "$fontFamilies.roboto-condensed",
          "fontWeight": "$fontWeights.roboto-condensed-1",
          "lineHeight": "$lineHeights.1",
          "fontSize": "$fontSize.1",
          "letterSpacing": "$letterSpacing.0",
          "paragraphSpacing": "$paragraphSpacing.0",
          "textCase": "$textCase.uppercase",
          "textDecoration": "$textDecoration.none"
        },
        "type": "typography"
      },
      "Navigation": {
        "value": {
          "fontFamily": "$fontFamilies.roboto-condensed",
          "fontWeight": "$fontWeights.roboto-condensed-1",
          "lineHeight": "$lineHeights.1",
          "fontSize": "$fontSize.1",
          "letterSpacing": "$letterSpacing.0",
          "paragraphSpacing": "$paragraphSpacing.0",
          "textCase": "$textCase.uppercase",
          "textDecoration": "$textDecoration.none"
        },
        "type": "typography"
      }
    },
    "Text": {
      "Dashboard": {
        "value": {
          "fontFamily": "$fontFamilies.roboto",
          "fontWeight": "$fontWeights.roboto-2",
          "lineHeight": "$lineHeights.2",
          "fontSize": "$fontSize.3",
          "letterSpacing": "$letterSpacing.0",
          "paragraphSpacing": "$paragraphSpacing.0",
          "textCase": "$textCase.none",
          "textDecoration": "$textDecoration.none"
        },
        "type": "typography"
      },
      "Basistext - Bold": {
        "value": {
          "fontFamily": "$fontFamilies.roboto",
          "fontWeight": "$fontWeights.roboto-3",
          "lineHeight": "$lineHeights.1",
          "fontSize": "$fontSize.1",
          "letterSpacing": "$letterSpacing.0",
          "paragraphSpacing": "$paragraphSpacing.0",
          "textCase": "$textCase.none",
          "textDecoration": "$textDecoration.none"
        },
        "type": "typography"
      },
      "Basistext": {
        "value": {
          "fontFamily": "$fontFamilies.roboto",
          "fontWeight": "$fontWeights.roboto-condensed-1",
          "lineHeight": "$lineHeights.1",
          "fontSize": "$fontSize.1",
          "letterSpacing": "$letterSpacing.0",
          "paragraphSpacing": "$paragraphSpacing.0",
          "textCase": "$textCase.none",
          "textDecoration": "$textDecoration.none"
        },
        "type": "typography"
      },
      "Description": {
        "value": {
          "fontFamily": "$fontFamilies.roboto",
          "fontWeight": "$fontWeights.roboto-condensed-1",
          "lineHeight": "$lineHeights.3",
          "fontSize": "$fontSize.0",
          "letterSpacing": "$letterSpacing.0",
          "paragraphSpacing": "$paragraphSpacing.0",
          "textCase": "$textCase.none",
          "textDecoration": "$textDecoration.none"
        },
        "type": "typography"
      },
      "Basistext - Italic": {
        "value": {
          "fontFamily": "$fontFamilies.roboto",
          "fontWeight": "$fontWeights.roboto-5",
          "lineHeight": "$lineHeights.1",
          "fontSize": "$fontSize.1",
          "letterSpacing": "$letterSpacing.0",
          "paragraphSpacing": "$paragraphSpacing.0",
          "textCase": "$textCase.none",
          "textDecoration": "$textDecoration.none"
        },
        "type": "typography"
      }
    },
    "Interactions": {
      "Links": {
        "value": {
          "fontFamily": "$fontFamilies.roboto",
          "fontWeight": "$fontWeights.roboto-condensed-1",
          "lineHeight": "$lineHeights.1",
          "fontSize": "$fontSize.1",
          "letterSpacing": "$letterSpacing.0",
          "paragraphSpacing": "$paragraphSpacing.0",
          "textCase": "$textCase.none",
          "textDecoration": "$textDecoration.none"
        },
        "type": "typography"
      },
      "Labels": {
        "value": {
          "fontFamily": "$fontFamilies.roboto",
          "fontWeight": "$fontWeights.roboto-condensed-1",
          "lineHeight": "$lineHeights.1",
          "fontSize": "$fontSize.1",
          "letterSpacing": "$letterSpacing.0",
          "paragraphSpacing": "$paragraphSpacing.0",
          "textCase": "$textCase.none",
          "textDecoration": "$textDecoration.none"
        },
        "type": "typography"
      },
      "Labels - Minor": {
        "value": {
          "fontFamily": "$fontFamilies.roboto",
          "fontWeight": "$fontWeights.roboto-condensed-1",
          "lineHeight": "$lineHeights.3",
          "fontSize": "$fontSize.0",
          "letterSpacing": "$letterSpacing.0",
          "paragraphSpacing": "$paragraphSpacing.0",
          "textCase": "$textCase.none",
          "textDecoration": "$textDecoration.none"
        },
        "type": "typography"
      },
      "Buttons": {
        "value": {
          "fontFamily": "$fontFamilies.roboto",
          "fontWeight": "$fontWeights.roboto-condensed-1",
          "lineHeight": "$lineHeights.1",
          "fontSize": "$fontSize.1",
          "letterSpacing": "$letterSpacing.0",
          "paragraphSpacing": "$paragraphSpacing.0",
          "textCase": "$textCase.none",
          "textDecoration": "$textDecoration.none"
        },
        "type": "typography"
      }
    },
    "textCase": {
      "uppercase": {
        "value": "uppercase",
        "type": "textCase"
      },
      "none": {
        "value": "none",
        "type": "textCase"
      }
    },
    "textDecoration": {
      "none": {
        "value": "none",
        "type": "textDecoration"
      }
    }
  }
}